conda2wheel/__init__.py
conda2wheel/__main__.py
conda2wheel-0.1.dist-info/DESCRIPTION.rst
conda2wheel-0.1.dist-info/METADATA
conda2wheel-0.1.dist-info/RECORD
conda2wheel-0.1.dist-info/WHEEL
conda2wheel-0.1.dist-info/entry_points.txt
conda2wheel-0.1.dist-info/metadata.json
conda2wheel-0.1.dist-info/top_level.txt
