Metadata-Version: 2.0
Name: conda2wheel
Version: 0.1
Summary: ``conda2wheel`` converts conda format packages to wheel format packages.
Home-page: https://github.com/aodag/conda2wheel
Author: Atsushi Odagiri
Author-email: aodagx@gmail.com
License: UNKNOWN
Platform: UNKNOWN
Requires-Dist: distlib
Requires-Dist: wheel
